rpls_py-0.3.2.dist-info/METADATA
rpls_py-0.3.2.dist-info/WHEEL
rpls_py.libs/libbrotlicommon-abf86ae9.so.1
rpls_py.libs/libfreetype-ccc6ae91.so.6
rpls_py.libs/libuuid-af7e79f9.so.1
rpls_py.libs/libfontconfig-7d688909.so.1
rpls_py.libs/libbrotlidec-db9dbda7.so.1
rpls_py.libs/libpng16-210ba03c.so.16
rpls_py/__init__.py
rpls_py/rpls_py.cpython-310-x86_64-linux-gnu.so
rpls_py-0.3.2.dist-info/RECORD
