Metadata-Version: 2.1
Name: rpls-py
Version: 0.3.2
Classifier: Programming Language :: Rust
Classifier: Programming Language :: Python :: Implementation :: CPython
Classifier: Programming Language :: Python :: Implementation :: PyPy
Summary: Python bindings to compute topological data analysis persistence landscapes using the fastest algorithm currently avalible: https://github.com/tph5595/rpls
Requires-Python: >=3.7
